gender/__init__.py
gender/getGender.py
gender/src/mlData/idf.pickle
gender/src/mlData/model.pkl
gender/src/mlData/vectorizer.pickle
python_gender-0.0.3.8.dist-info/LICENSE
python_gender-0.0.3.8.dist-info/METADATA
python_gender-0.0.3.8.dist-info/WHEEL
python_gender-0.0.3.8.dist-info/top_level.txt
python_gender-0.0.3.8.dist-info/RECORD
