Metadata-Version: 2.1
Name: python-gender
Version: 0.0.3.8
Summary: A python gender classification package
Home-page: https://github.com/aime-risson/python-gender-api
Author: Aimé Risson
Author-email: aime.risson.1@gmail.com
License: UNKNOWN
Platform: UNKNOWN
Classifier: Programming Language :: Python :: 3
Classifier: License :: OSI Approved :: MIT License
Classifier: Operating System :: OS Independent
Requires-Python: >=3.6
Requires-Dist: joblib
Requires-Dist: pandas
